gnupg.py
python_gnupg-0.4.7.dist-info/LICENSE.txt
python_gnupg-0.4.7.dist-info/METADATA
python_gnupg-0.4.7.dist-info/WHEEL
python_gnupg-0.4.7.dist-info/top_level.txt
python_gnupg-0.4.7.dist-info/RECORD
